pawser/__init__.py
pawser/parser.py
pawser-1.0.1.dist-info/licenses/LICENSE
pawser-1.0.1.dist-info/METADATA
pawser-1.0.1.dist-info/WHEEL
pawser-1.0.1.dist-info/top_level.txt
pawser-1.0.1.dist-info/RECORD
